nrl_sdk_lib/models/__init__.py
nrl_sdk_lib/models/crs.py
nrl_sdk_lib/models/feature_collection.py
nrl_sdk_lib/models/geometry.py
nrl_sdk_lib/models/job.py
nrl_sdk_lib/models/result.py
nrl_sdk_lib-0.2.9.dist-info/METADATA
nrl_sdk_lib-0.2.9.dist-info/WHEEL
nrl_sdk_lib-0.2.9.dist-info/RECORD
