Metadata-Version: 2.4
Name: nrl-sdk-lib
Version: 0.2.9
Summary: A library for working with the NRL SDK
Project-URL: Homepage, https://github.com/3lbits/nrl-sdk
Project-URL: Documentation, https://3lbits.github.io/nrl-sdk/
Project-URL: Repository, https://github.com/3lbits/nrl-sdk.git
Project-URL: Issues, https://github.com/3lbits/nrl-sdk/issues
License-Expression: Apache-2.0
Requires-Python: >=3.13
Requires-Dist: pydantic>=2.11.7
